setup.py
acaptain/__init__.py
acaptain/command_line.py
acaptain.egg-info/PKG-INFO
acaptain.egg-info/SOURCES.txt
acaptain.egg-info/dependency_links.txt
acaptain.egg-info/entry_points.txt
acaptain.egg-info/top_level.txt