Metadata-Version: 1.0
Name: acaptain
Version: 00.00.01
Summary: Farm monitoring
Home-page: http://pypi.python.org/pypi/acaptain/
Author: Alectryon LLC
Author-email: mbiedler@gmail.com
License: license.txt
Platform: UNKNOWN
